README.md
setup.py
realestate_com_au/__init__.py
realestate_com_au/realestate_com_au.py
realestate_com_au/settings.py
realestate_com_au/graphql/__init__.py
realestate_com_au/graphql/searchBuy.py
realestate_com_au/graphql/searchRent.py
realestate_com_au/utils/__init__.py
realestate_com_au_api.egg-info/PKG-INFO
realestate_com_au_api.egg-info/SOURCES.txt
realestate_com_au_api.egg-info/dependency_links.txt
realestate_com_au_api.egg-info/requires.txt
realestate_com_au_api.egg-info/top_level.txt