Metadata-Version: 2.1
Name: realestate-com-au-api
Version: 0.0.1b1
Summary: Python wrapper for the realestate.com.au API
Home-page: https://github.com/tomquirk/realesate-com-au-api
Author: Tom Quirk
Author-email: tomquirkacc@gmail.com
License: MIT
Platform: UNKNOWN
Classifier: Programming Language :: Python :: 3
Classifier: License :: OSI Approved :: MIT License
Classifier: Operating System :: OS Independent
